zx2xberry/__init__.py
zx2xberry/main.py
zx2xberry/prompts.py
zx2xberry-2025.12.21201323.dist-info/METADATA
zx2xberry-2025.12.21201323.dist-info/WHEEL
zx2xberry-2025.12.21201323.dist-info/top_level.txt
zx2xberry-2025.12.21201323.dist-info/RECORD
