Metadata-Version: 2.4
Name: zx2xberry
Version: 2025.12.21201323
Summary: zx2xberry translates ZX Spectrum+ keyboard keypresses into commands for XBerry Pi devices.
Author-email: zx2xberry <hi@eugene.plus>
License: MIT
Project-URL: Homepage, https://github.com/chigwell/zx2xberry
Requires-Python: >=3.9
Requires-Dist: langchain-llm7>=0.0.0
Requires-Dist: llmatch-messages>=0.0.0
Requires-Dist: langchain-core>=0.3.0
